{
                "private_path": "private/vaillant_vrt340f.c",
                "private_start_line": 64,
                "private_end_line": 91,
                "detailed information of clone fragments": {
                                "modify within sentence": {
                                                "add/delete identifiers, operators": [],
                                                "modify identifiers, variables": "",
                                                "modify operators": [],
                                                "rearrangement  of a sentence": [],
                                                "other": []
                                },
                                "add/delete sentence": [
                                    {
                                        "private": "78,82",
                                        "os": ""
                                    }
                                ],
                                "add/delete/modify comment": "",
                                "rearrangement of code": [
                                    {
                                        "private": "67,71",
                                        "os": "141,145"
                                    }
                                ]
                },
                "Type": "",
                "Scenarios": {
                                "should be identify": "",
                                "scenario": "commuinty code",
                                "specific scenario": "similar algorithm or function"
                },
                "granularity": "function",
                "os_path": "open_source/trie.c",
                "os_path_start_line": 138,
                "os_path_end_line": 161
}